codetable/__init__.py
codetable/code.py
codetable/codes.py
codetable/codes_storage.py
codetable/config.py
codetable/types.py
codetable-1.0.9.dist-info/licenses/LICENSE
codetable-1.0.9.dist-info/METADATA
codetable-1.0.9.dist-info/WHEEL
codetable-1.0.9.dist-info/top_level.txt
codetable-1.0.9.dist-info/RECORD
