Metadata-Version: 2.4
Name: codetable
Version: 1.0.9
Summary: Codetable is a lightweight package for seamlessly setting up codes, such as those used in API responses.
Home-page: https://github.com/0x1618/codetable
Author: Maksymilian Sawicz
Classifier: Programming Language :: Python :: 3
Classifier: License :: OSI Approved :: MIT License
Classifier: Operating System :: OS Independent
Requires-Python: >=3.10
License-File: LICENSE
Dynamic: author
Dynamic: classifier
Dynamic: description
Dynamic: description-content-type
Dynamic: home-page
Dynamic: license-file
Dynamic: requires-python
Dynamic: summary
